filtercascade/__init__.py
filtercascade/test.py
filtercascade-0.2.1.dist-info/LICENSE
filtercascade-0.2.1.dist-info/METADATA
filtercascade-0.2.1.dist-info/WHEEL
filtercascade-0.2.1.dist-info/top_level.txt
filtercascade-0.2.1.dist-info/RECORD
