Metadata-Version: 2.1
Name: filtercascade
Version: 0.2.1
Summary: A simple bloom filter cascade implementation in Python
Home-page: http://github.com/mozmark/filter-cascade
Author: Mark Goodwin
Author-email: mgoodwin@mozilla.com
License: Mozilla Public License 2.0 (MPL 2.0)
Keywords: bloom filter cascade multi level mlbf
Platform: UNKNOWN
Classifier: Development Status :: 5 - Production/Stable
Classifier: License :: OSI Approved :: Mozilla Public License 2.0 (MPL 2.0)
Classifier: Programming Language :: Python :: 3
Requires-Dist: bitarray (>=0.9.2)
Requires-Dist: mmh3 (>=2.5.1)
